epymetheus/__init__.py
epymetheus/_utils.py
epymetheus/benchmarks/__init__.py
epymetheus/benchmarks/buy_and_hold.py
epymetheus/benchmarks/determined.py
epymetheus/benchmarks/dumb.py
epymetheus/benchmarks/random.py
epymetheus/datasets/__init__.py
epymetheus/datasets/_utils.py
epymetheus/datasets/randomwalk.py
epymetheus/datasets/usstocks.py
epymetheus/datasets/usstocks.txt
epymetheus/exceptions.py
epymetheus/metrics/__init__.py
epymetheus/metrics/metrics.py
epymetheus/metrics/name.py
epymetheus/stochastic/__init__.py
epymetheus/stochastic/brownian.py
epymetheus/strategy/__init__.py
epymetheus/strategy/base.py
epymetheus/strategy/container.py
epymetheus/trade.py
epymetheus/ts/__init__.py
epymetheus/ts/ts.py
epymetheus/utils.py
epymetheus-0.17.1.dist-info/LICENSE
epymetheus-0.17.1.dist-info/WHEEL
epymetheus-0.17.1.dist-info/METADATA
epymetheus-0.17.1.dist-info/RECORD
