Metadata-Version: 2.1
Name: epymetheus
Version: 0.17.1
Summary: Multi-asset Backtesting Framework
Home-page: https://github.com/epymetheus/epymetheus
License: BSD-3-Clause
Author: Shota Imaki
Author-email: shota.imaki.0801@gmail.com
Requires-Python: >=3.7.12,<3.11
Classifier: License :: OSI Approved :: BSD License
Classifier: Programming Language :: Python :: 3
Classifier: Programming Language :: Python :: 3.10
Classifier: Programming Language :: Python :: 3.8
Classifier: Programming Language :: Python :: 3.9
Requires-Dist: numpy (>=1.21.4,<2.0.0)
Requires-Dist: pandas (>=1.3.4,<2.0.0)
Requires-Dist: pandas-datareader (>=0.10.0,<0.11.0)
Project-URL: Repository, https://github.com/epymetheus/epymetheus
